gsmmodem/__init__.py
gsmmodem/compat.py
gsmmodem/exceptions.py
gsmmodem/gprs.py
gsmmodem/modem.py
gsmmodem/pdu.py
gsmmodem/serial_comms.py
gsmmodem/util.py
gsmtermlib/__init__.py
gsmtermlib/atcommands.py
gsmtermlib/posoptparse.py
gsmtermlib/terminal.py
gsmtermlib/trie.py
python_gsmmodem_2025-0.1.3.data/scripts/gsmterm.py
python_gsmmodem_2025-0.1.3.data/scripts/identify-modem.py
python_gsmmodem_2025-0.1.3.data/scripts/sendsms.py
python_gsmmodem_2025-0.1.3.dist-info/licenses/AUTHORS
python_gsmmodem_2025-0.1.3.dist-info/licenses/COPYING
python_gsmmodem_2025-0.1.3.dist-info/METADATA
python_gsmmodem_2025-0.1.3.dist-info/WHEEL
python_gsmmodem_2025-0.1.3.dist-info/top_level.txt
python_gsmmodem_2025-0.1.3.dist-info/RECORD
